{
  "industryId": "retail",
  "industryName": "小売業",
  "source": "金融庁『業種別支援の着眼点』（2023年3月公表、2026年3月補足資料を含む公開PDF P.24-32）https://www.fsa.go.jp/policy/chuukai/gyousyubetu.html",
  "sections": {
    "basics": {
      "title": "基本原則・商圏",
      "items": [
        {
          "id": "retail-basics-01",
          "title": "中小規模の小売業 戦いの基本原則",
          "checkpoints": [
            "自ら品質や味といった差別化を創造することが困難な業種",
            "品揃え・専門知識・アフターサービス等が事業性を見極めるポイント",
            "取引先企業の「こだわり」が競争相手にどのくらい対抗できるかを冷静に判断"
          ],
          "keyQuestion": "大手量販店やWeb販売との対抗軸はどこにあるか？"
        },
        {
          "id": "retail-basics-02",
          "title": "専門性の理解",
          "checkpoints": [
            "その分野自体の理解を自分自身の努力である程度深めないと事業性を目利きできない",
            "SNSやインターネット等に様々な分野の情報が存在するので理解深耕に活用する"
          ],
          "keyQuestion": "汗をかいて理解するしかない「専門性」の難しさを認識しているか？"
        }
      ]
    },
    "financials": {
      "title": "決算資料編",
      "items": [
        {
          "id": "retail-fin-01",
          "title": "総資本回転率",
          "checkpoints": [
            "小売業は事業資産を繰り回して、どれだけ売上高を確保しているかが基軸",
            "3年程度の傾向で事業全体の大まかな流れをつかむ",
            "自社物件か賃貸物件かにより数値の変化もある"
          ],
          "keyQuestion": "ROAを分解して、総資本回転率と売上高利益率のどちらに課題があるか？",
          "relatedFinancial": "売上高,総資産"
        },
        {
          "id": "retail-fin-02",
          "title": "売上高総利益率",
          "checkpoints": [
            "取扱品目によって大きく変化、規模による違いも大きい",
            "他社比較よりも自社の3年程度の傾向をみるとよい",
            "小売業の平均で3割ぐらいの粗利率"
          ],
          "benchmarks": {
            "機械機器小売業": "25.14%",
            "スーパー平均": "26.11%",
            "小売業全体平均": "30.92%",
            "飲食料品小売業": "32.11%",
            "無店舗小売業": "41.15%",
            "織物・衣服・身の回り品小売業": "44.81%"
          },
          "keyQuestion": "事業を継続していける粗利が取れているか？ここ数年の傾向はどうか？",
          "relatedFinancial": "売上総利益"
        },
        {
          "id": "retail-fin-03",
          "title": "経常利益（雑収入・リベート）",
          "checkpoints": [
            "メーカーや問屋からリベートが支払われることが多い",
            "リベートは決算書上で雑収入として扱われることが多い",
            "リベートの金額・内容に注視して実際の本業収益の傾向を把握する"
          ],
          "keyQuestion": "雑収入の内訳は確認可能か？リベートなら売上高との比率を確認",
          "relatedFinancial": "雑収入"
        }
      ]
    },
    "visit": {
      "title": "訪問時編",
      "items": [
        {
          "id": "retail-visit-01",
          "title": "売場面積",
          "checkpoints": [
            "売場面積を把握していないことが多いので確認する",
            "従業員1人当たりの管理可能面積の目安を持つ",
            "目安と実態の差異が大きい場合はオペレーションの理解を深める"
          ],
          "benchmarks": { "従業員1人当たり管理可能面積": "8～10坪程度" },
          "keyQuestion": "1人当たりの管理可能面積は適正か？"
        },
        {
          "id": "retail-visit-02",
          "title": "取扱アイテム数・売れ筋商品",
          "checkpoints": [
            "業種・業態、季節等により変動が大きいが大まかな把握は必須",
            "発注台帳の確認や仕入先への問い合わせで把握可能",
            "棚卸資産回転日数の短縮や効率の良い発注が課題"
          ],
          "benchmarks": { "従業員1人当たり管理可能アイテム数": "約80～100アイテム" },
          "keyQuestion": "人が管理できる面積やアイテム数を把握し、実行可能な改善範囲を理解しているか？"
        },
        {
          "id": "retail-visit-03",
          "title": "売上高構成式ベースのヒアリング",
          "checkpoints": [
            "売上高＝客数×客単価",
            "客数＝入店客数×買上率",
            "客単価＝平均買上点数×平均商品単価",
            "詳細なデータの管理をしていないケースが多い"
          ],
          "keyQuestion": "売上高の内訳の把握と推計はできているか？"
        },
        {
          "id": "retail-visit-04",
          "title": "差別化要素の確認",
          "checkpoints": [
            "大手量販店やWeb販売との対抗軸はどこにあるか",
            "差別化の3類型: 専門性、保守・修繕、関係性",
            "小売業は飲食業と違い「味」という強い差別化要素がない"
          ],
          "keyQuestion": "自分がお客様なら、どこが「差別化」のポイントと感じるか？"
        }
      ]
    },
    "cases": []
  },
  "zeimuExtensions": {
    "note": "以下はZeimu AI独自の補足情報であり、金融庁原典には含まれません"
  }
}
